[{"__type__":"cc.SpriteFrame","content":{"name":"0","texture":"33PRc/F3hNtpJ5MEOiZ881","rect":[0,0,171,254],"offset":[0,0],"originalSize":[171,254],"capInsets":[0,0,0,0]}},[{"__type__":"cc.Prefab","_name":"DefensePlayer","data":{"__id__":1}},{"__type__":"cc.Node","_name":"DefensePlayer","_components":[{"__type__":"cc.Sprite","_name":"DefensePlayer<Sprite>","node":{"__id__":1},"_materials":[{"__uuid__":"ecpdLyjvZBwrvm+cedCcQy"}],"_spriteFrame":{"__uuid__":"47r/ImUt9ECqitwKVec8mO"}},{"__type__":"cc.RigidBody","node":{"__id__":1},"_type":0,"enabledContactListener":true},{"__type__":"cc.PhysicsCircleCollider","node":{"__id__":1},"_radius":90},{"__type__":"cc.CircleCollider","node":{"__id__":1},"_radius":90},{"__type__":"e6cbaFQqmRGy7UkmC5o0Gse","node":{"__id__":1},"power":4},{"__type__":"f558c17PSZMPJTtistmKHmr","node":{"__id__":1}}],"_prefab":{"__type__":"cc.PrefabInfo","root":{"__id__":1},"asset":{"__uuid__":"94Cw6TJtpOapYe4WhmzDS3"},"fileId":"48rcE/+LlPvZo13ftHmphi"},"_contentSize":{"__type__":"cc.Size","width":171,"height":254},"_trs":{"__type__":"TypedArray","ctor":"Float64Array","array":[-6.4,-136.9,0,0,0,0,1,0.45,0.45,1]}}]]